paperman/__init__.py
paperman/__main__.py
paperman/cfg.py
paperman/finder.py
paperman/io.py
paperman/project.py
paperman/utils.py
paperman/parser/__init__.py
paperman/parser/bib.py
paperman/parser/cite.py
paperman/parser/common.py
paperman/parser/img.py
paperman/parser/journal.py
paperman/parser/tex.py
paperman/subcommands/__init__.py
paperman/subcommands/bib.py
paperman/subcommands/clean.py
paperman/subcommands/collect.py
paperman/subcommands/common.py
paperman/subcommands/config.py
paperman/subcommands/diff.py
paperman/subcommands/img.py
paperman/subcommands/inp.py
paperman/subcommands/journal.py
paperman/subcommands/lib.py
paperman/subcommands/lint.py
paperman/subcommands/sort_authors.py
paperman/subcommands/sync.py
paperman-1.1.1.dist-info/METADATA
paperman-1.1.1.dist-info/WHEEL
paperman-1.1.1.dist-info/entry_points.txt
paperman-1.1.1.dist-info/licenses/LICENSE.txt
paperman-1.1.1.dist-info/RECORD
