Metadata-Version: 2.4
Name: paperman
Version: 1.1.1
Summary: latex project and bibliography management utility
Project-URL: Homepage, https://github.com/zaphB/paperman
Project-URL: Repository, https://github.com/zaphB/paperman.git
Author-email: Philipp Bredol <philipp.bredol@rwth-aachen.de>
License: MIT License
License-File: LICENSE.txt
Requires-Python: >=3.11
Requires-Dist: appdirs
Requires-Dist: argcomplete
Requires-Dist: argparse
Requires-Dist: numpy
Requires-Dist: pyiso4
Requires-Dist: pyyaml
Requires-Dist: unidecode
